MANIFEST.in
README.rst
setup.py
syro/korg_syro_comp.c
syro/korg_syro_func.c
syro/korg_syro_volcasample.c
volcasample/__init__.py
volcasample/audio.py
volcasample/cli.py
volcasample/main.py
volcasample/project.py
volcasample/syro.py
volcasample.egg-info/PKG-INFO
volcasample.egg-info/SOURCES.txt
volcasample.egg-info/dependency_links.txt
volcasample.egg-info/entry_points.txt
volcasample.egg-info/not-zip-safe
volcasample.egg-info/requires.txt
volcasample.egg-info/top_level.txt
volcasample/../COPYING
volcasample/../syro/korg_syro_comp.c
volcasample/../syro/korg_syro_comp.h
volcasample/../syro/korg_syro_func.c
volcasample/../syro/korg_syro_func.h
volcasample/../syro/korg_syro_type.h
volcasample/../syro/korg_syro_volcasample.c
volcasample/../syro/korg_syro_volcasample.h
volcasample/doc/api.rst
volcasample/doc/cli.rst
volcasample/doc/index.rst
volcasample/doc/quickstart.rst
volcasample/doc/html/api.html
volcasample/doc/html/cli.html
volcasample/doc/html/genindex.html
volcasample/doc/html/index.html
volcasample/doc/html/py-modindex.html
volcasample/doc/html/quickstart.html
volcasample/doc/html/search.html
volcasample/doc/html/searchindex.js
volcasample/doc/html/_sources/api.rst.txt
volcasample/doc/html/_sources/cli.rst.txt
volcasample/doc/html/_sources/index.rst.txt
volcasample/doc/html/_sources/quickstart.rst.txt
volcasample/doc/html/_static/basic.css
volcasample/doc/html/_static/doctools.js
volcasample/doc/html/_static/documentation_options.js
volcasample/doc/html/_static/file.png
volcasample/doc/html/_static/jquery-3.2.1.js
volcasample/doc/html/_static/jquery.js
volcasample/doc/html/_static/language_data.js
volcasample/doc/html/_static/minus.png
volcasample/doc/html/_static/plus.png
volcasample/doc/html/_static/pygments.css
volcasample/doc/html/_static/searchtools.js
volcasample/doc/html/_static/underscore-1.3.1.js
volcasample/doc/html/_static/underscore.js
volcasample/doc/html/_static/css/badge_only.css
volcasample/doc/html/_static/css/theme.css
volcasample/doc/html/_static/js/modernizr.min.js
volcasample/doc/html/_static/js/theme.js
volcasample/test/__init__.py
volcasample/test/test_audio.py
volcasample/test/test_project.py
volcasample/test/test_syro.py
