Metadata-Version: 2.1
Name: volcasample
Version: 0.6.0
Summary: Python wrapping of KORG Volca sample utilities.
Home-page: https://github.com/tundish/volcasample
Author: D Haynes
Author-email: tundish@thuswise.org
License: UNKNOWN
Platform: UNKNOWN
Classifier: Operating System :: OS Independent
Classifier: Programming Language :: Python :: 3.4
Classifier: Programming Language :: Python :: 3.5
Classifier: License :: OSI Approved :: GNU General Public License v3 or later (GPLv3+)
Provides-Extra: audio
Provides-Extra: dev
Provides-Extra: docbuild
